celerylogger/__init__.py
celerylogger/celery_logger.py
celery_logger-0.0.3.dist-info/LICENCE
celery_logger-0.0.3.dist-info/METADATA
celery_logger-0.0.3.dist-info/WHEEL
celery_logger-0.0.3.dist-info/entry_points.txt
celery_logger-0.0.3.dist-info/top_level.txt
celery_logger-0.0.3.dist-info/RECORD
