Metadata-Version: 2.1
Name: celery-logger
Version: 0.0.3
Summary: Python library for logging celery events
Home-page: https://github.com/CraveFood/celery-logger
Author: Thiago Ferreira
Author-email: th.thiago96@gmail.com
License: BSD license
Keywords: logging,celery
Platform: UNKNOWN
Classifier: Development Status :: 2 - Pre-Alpha
Classifier: Intended Audience :: Developers
Classifier: License :: OSI Approved :: BSD License
Classifier: Topic :: Software Development :: Libraries :: Python Modules
Classifier: Natural Language :: English
Classifier: Programming Language :: Python :: 3
Classifier: Programming Language :: Python :: 3.5
Classifier: Programming Language :: Python :: 3.6
Classifier: Programming Language :: Python :: 3.7
Classifier: Programming Language :: Python :: 3.8
Requires-Python: >=3.7
License-File: LICENCE
Requires-Dist: celery[redis] (==4.3.1)
